calculator_package/__init__.py
calculator_package_nazmul-0.0.1.dist-info/licenses/LICENSE
calculator_package_nazmul-0.0.1.dist-info/METADATA
calculator_package_nazmul-0.0.1.dist-info/WHEEL
calculator_package_nazmul-0.0.1.dist-info/top_level.txt
calculator_package_nazmul-0.0.1.dist-info/RECORD
